LICENSE.txt
MANIFEST.in
README.md
README.srt
setup.cfg
setup.py
data/test/struct/3x3x3_test_shrunk_fbc.chk
data/test/struct/3x3x3_test_shrunk_pbc.chk
data/test/types/generate_test_types.py
data/test/types/type_shrunk.pickle
data/test/types/type_test.pickle
data/uio66/struct/3x3x3_0.chk
data/uio66/struct/3x3x3_1.chk
data/uio66/struct/3x3x3_2.chk
data/uio66/struct/3x3x3_3.chk
data/uio66/struct/3x3x3_4.chk
data/uio66/struct/3x3x3_5.chk
data/uio66/struct/3x3x3_6.chk
data/uio66/struct/3x3x3_7.chk
data/uio66/struct/3x3x3_8.chk
data/uio66/types/generate_fcu_type.py
data/uio66/types/generate_reo_type.py
data/uio66/types/type_fcu.pickle
data/uio66/types/type_reo.pickle
docs/Makefile
docs/common.py
docs/conf.py
docs/constructing_systems.rst
docs/creating_types.rst
docs/index.rst
docs/installation.rst
docs/make.bat
docs/objects.inv
docs/performing_simulations.rst
docs/rg_micmec.rst
docs/rg_micmec_analysis.rst
docs/rg_micmec_builder.rst
docs/rg_micmec_pes.rst
docs/rg_micmec_sampling.rst
docs/updatelibdoc.py
docs/figs/core_routines.png
docs/figs/micmec_proc_wide.png
docs/thesis/thesis.pdf
micmec/__init__.py
micmec/log.py
micmec/system.py
micmec/utils.py
micmec.egg-info/PKG-INFO
micmec.egg-info/SOURCES.txt
micmec.egg-info/dependency_links.txt
micmec.egg-info/entry_points.txt
micmec.egg-info/not-zip-safe
micmec.egg-info/top_level.txt
micmec/analysis/__init__.py
micmec/analysis/advanced.py
micmec/analysis/basic.py
micmec/analysis/tensor.py
micmec/analysis/utils.py
micmec/builder/__init__.py
micmec/builder/builder.py
micmec/builder/builder_io.py
micmec/pes/__init__.py
micmec/pes/mmff.py
micmec/pes/nanocell.py
micmec/pes/nanocell_jax.py
micmec/pes/nanocell_original.py
micmec/pes/nanocell_thesis.py
micmec/sampling/__init__.py
micmec/sampling/dof.py
micmec/sampling/iterative.py
micmec/sampling/npt.py
micmec/sampling/nvt.py
micmec/sampling/opt.py
micmec/sampling/trajectory.py
micmec/sampling/utils.py
micmec/sampling/verlet.py
simulations/add_numbers.py
simulations/md.py
simulations/optimisation.py
simulations/relaxed_scan.py
simulations/static_scan.py