Metadata-Version: 2.1
Name: micmec
Version: 1.0
Summary: The first implementation of the micromechanical model, ever.
License: GNU General Public License v3 or later (GPLv3+)
Keywords: coarse graining,molecular dynamics,metal-organic frameworks
Classifier: Environment :: Console
Classifier: Operating System :: POSIX :: Linux
Classifier: Programming Language :: Python :: 3
Classifier: Topic :: Scientific/Engineering :: Physics
Classifier: Intended Audience :: Science/Research
License-File: LICENSE.txt
